codec/__init__.py
codec/auth.py
codec/client.py
codec/constants.py
codec/exceptions.py
codec/resources/__init__.py
codec/resources/collections.py
codec/resources/logger.py
codec/resources/request.py
codec/resources/search.py
codec/resources/videos.py
codec/resources/utils/__init__.py
codec/resources/utils/utils.py
codec/resources/utils/webhook.py
codec/utils/__init__.py
codec/utils/file_utils.py
codec/utils/format.py
codec_video-0.1.0.dist-info/LICENSE
codec_video-0.1.0.dist-info/WHEEL
codec_video-0.1.0.dist-info/METADATA
codec_video-0.1.0.dist-info/RECORD
