Metadata-Version: 2.1
Name: codec-video
Version: 0.1.0
Summary: Python Library for the Codec API
Author-email: Armada Labs Inc <contact@codec.io>
Requires-Python: >=3.8
Classifier: License :: OSI Approved :: MIT License
Requires-Dist: requests >=2.31.0
Requires-Dist: supabase >=1.0.3
Requires-Dist: svix >=1.21.0
Project-URL: Documentation, https://docs.codec.io
Project-URL: Home, https://codec.io
Project-URL: Source, https://github.com/codec-hq/codec-py
